takollama/ChatWindow.py
takollama/RAG.py
takollama/TextExtractor.py
takollama/VectorDB.py
takollama/__init__.py
takollama/main.py
takollama/preprocess_text.py
takollama/scripts/RAG_query.py
takollama/scripts/TextExtractor.py
takollama/scripts/__init__.py
takollama/scripts/addurltodbcolab.py
takollama/scripts/createDBColab.py
takollama/scripts/createDBlocal.py
takollama/scripts/create_embeddings.py
takollama/scripts/create_rag_pipeline.py
takollama/scripts/demo_colab.py
takollama/scripts/demo_colab_2.py
takollama/scripts/extract_text.py
takollama/scripts/generate_embeddings.py
takollama/scripts/libtest.py
takollama/scripts/make_DB_colab.py
takollama/scripts/ollama_gpu_selector.sh
takollama/scripts/preprocess_text.py
takollama/scripts/queries.py
takollama/scripts/querydb.py
takollama/scripts/test.ipynb
takollama/scripts/test.py
takollama/scripts/testRAG.py
takollama/scripts/urls.txt
takollama-0.2.1.dist-info/licenses/LICENSE
takollama-0.2.1.dist-info/METADATA
takollama-0.2.1.dist-info/WHEEL
takollama-0.2.1.dist-info/entry_points.txt
takollama-0.2.1.dist-info/top_level.txt
takollama-0.2.1.dist-info/RECORD
