Metadata-Version: 2.4
Name: takollama
Version: 0.2.1
Summary: RAG library
Requires-Python: >=3.10
License-File: LICENSE
Requires-Dist: bs4>=0.0.2
Requires-Dist: chromadb>=1.0.17
Requires-Dist: langchain-community>=0.3.27
Requires-Dist: ollama>=0.5.3
Requires-Dist: pypdf>=6.0.0
Dynamic: license-file
